{
  "kind": "collectionType",
  "collectionName": "rentals",
  "info": {
    "singularName": "rental",
    "pluralName": "rentals",
    "displayName": "rentals",
    "description": ""
  },
  "options": {
    "draftAndPublish": true
  },
  "pluginOptions": {},
  "attributes": {
    "start_date": {
      "type": "date"
    },
    "end_date": {
      "type": "date"
    },
    "apartment": {
      "type": "relation",
      "relation": "oneToOne",
      "target": "api::apartament.apartament"
    },
    "price": {
      "type": "decimal"
    },
    "currency": {
      "type": "enumeration",
      "enum": [
        "USD",
        "UYU"
      ]
    },
    "user": {
      "type": "relation",
      "relation": "oneToOne",
      "target": "plugin::users-permissions.user"
    }
  }
}
